{
  "title": "Sunshine Kids",
  "publishedAt": "13th Sep 2020",
  "content": "## Project Specification\n\n* Class: Advance Typography\n* Design Tool: Figma\n* Desktop Prototype\n* Source Code: [View on Github](https://github.com/JaimeGG64/sunshine-kids)\n\n## Problem\n\nGenerally non-profits does not have the resources to develop a polish landing page. Sunshine kids is one example. The goals of this redesign to make the home page inviting but informative as well.\n\n![old-shine-kids home page](/images/uploads/old-sunshine-kids-website.png)\n\nOld Sunshine Kids Page\n\n## Sketches\n\n![Pencil sketches for sunshine kids home page](/images/uploads/sunshine-kids-sketches.jpg)\n\n## Low-Fi Wireframe\n\n![Low-Fi Wireframe for sunshine kids](/images/uploads/sunshine-kids-low-fi.png)\n\n## Hi-Fi Wireframe\n\n![](/images/uploads/art-343-website-design-desktop.png)",
  "seoDescription": "A redesign of the Sunshine Kids landing page",
  "featuredImage": "/images/uploads/sunshine-kids-feature.png"
}